pyabhata/__init__.py
pyabhata/pyabhata.py
pyabhata-0.3.dist-info/METADATA
pyabhata-0.3.dist-info/WHEEL
pyabhata-0.3.dist-info/top_level.txt
pyabhata-0.3.dist-info/RECORD
