Metadata-Version: 2.1
Name: pyabhata
Version: 0.3
Summary: A mathematical library honoring Aryabhata
Author: TheYellowAstronaut
Author-email: malli.advait0@gmail.com
Classifier: Programming Language :: Python :: 3
Classifier: License :: OSI Approved :: MIT License
Classifier: Operating System :: OS Independent
Requires-Dist: python-math
